npdep_transfer/__init__.py
npdep_transfer/__main__.py
npdep_transfer/args/Args.py
npdep_transfer/args/__init__.py
npdep_transfer/base/Transfer.py
npdep_transfer/base/__init__.py
npdep_transfer/module/__init__.py
npdep_transfer/module/dep/DepDataExfiltration.py
npdep_transfer/module/dep/DepFileExfiltration.py
npdep_transfer/module/dep/__init__.py
npdep_transfer/module/depOverHttp/DepOverHttp.py
npdep_transfer/module/depOverHttp/__init__.py
npdep_transfer/module/icmp/IcmpEcho.py
npdep_transfer/module/icmp/__init__.py
npdep_transfer/output/Output.py
npdep_transfer/output/__init__.py
npdep_transfer/util/Util.py
npdep_transfer/util/__init__.py
npdep_transfer-0.1.0.dist-info/METADATA
npdep_transfer-0.1.0.dist-info/WHEEL
npdep_transfer-0.1.0.dist-info/entry_points.txt
npdep_transfer-0.1.0.dist-info/top_level.txt
npdep_transfer-0.1.0.dist-info/RECORD
