Metadata-Version: 2.1
Name: npdep_transfer
Version: 0.1.0
Summary: Transfer Modules for Network Protocol Data Exfiltration Project Client
Home-page: https://github.com/npdep/npdep-transfer
Author: npdep
Classifier: Operating System :: OS Independent 
Classifier: Programming Language :: Python :: 3 
Requires-Dist: dep-common
Requires-Dist: dep-client
Requires-Dist: npdep-icmp-client
Requires-Dist: npdep-http-client
Requires-Dist: foi
